wolfsoftware/drawlines/__init__.py
wolfsoftware/drawlines/drawlines.py
wolfsoftware.drawlines-0.1.3.dist-info/LICENSE.md
wolfsoftware.drawlines-0.1.3.dist-info/METADATA
wolfsoftware.drawlines-0.1.3.dist-info/WHEEL
wolfsoftware.drawlines-0.1.3.dist-info/top_level.txt
wolfsoftware.drawlines-0.1.3.dist-info/RECORD
