Metadata-Version: 2.1
Name: wolfsoftware.drawlines
Version: 0.1.3
Summary: Draw lines on the console with optional text.
Home-page: https://github.com/DevelopersToolbox/draw-lines-package
Author: Wolf Software
Author-email: pypi@wolfsoftware.com
License: MIT
Project-URL: Source, https://github.com/DevelopersToolbox/draw-lines-package
Project-URL: Tracker, https://github.com/DevelopersToolbox/draw-lines-package/issues/
Project-URL: Documentation, https://github.com/DevelopersToolbox/draw-lines-package
Project-URL: Sponsor, https://github.com/sponsors/WolfSoftware
Keywords: python,convert_size
Classifier: Development Status :: 4 - Beta
Classifier: Environment :: Console
Classifier: Intended Audience :: Developers
Classifier: License :: OSI Approved :: MIT License
Classifier: Programming Language :: Python :: 3
Classifier: Programming Language :: Python :: 3.9
Classifier: Programming Language :: Python :: 3.10
Classifier: Programming Language :: Python :: 3.11
Classifier: Programming Language :: Python :: 3.12
Classifier: Operating System :: OS Independent
Classifier: Topic :: Software Development
Requires-Python: >=3.9
License-File: LICENSE.md
Requires-Dist: colorama ==0.4.6
